{
  "aggregate": {
    "counters": {
      "vusers.created_by_name.Cenário 100 usuários": 3000,
      "vusers.created": 3000,
      "http.requests": 9000,
      "http.codes.200": 9000,
      "http.responses": 9000,
      "http.downloaded_bytes": 603000,
      "plugins.metrics-by-endpoint./posts.codes.200": 3000,
      "plugins.metrics-by-endpoint./users.codes.200": 3000,
      "plugins.metrics-by-endpoint./comments.codes.200": 3000,
      "vusers.failed": 0,
      "vusers.completed": 3000
    },
    "rates": {
      "http.request_rate": 311
    },
    "firstCounterAt": 1763429065721,
    "firstHistogramAt": 1763429065734,
    "lastCounterAt": 1763429096987,
    "lastHistogramAt": 1763429096987,
    "firstMetricAt": 1763429065721,
    "lastMetricAt": 1763429096987,
    "period": 1763429090000,
    "summaries": {
      "http.response_time": {
        "min": 0,
        "max": 33,
        "count": 9000,
        "mean": 0.3,
        "p50": 0,
        "median": 0,
        "p75": 1,
        "p90": 1,
        "p95": 1,
        "p99": 1,
        "p999": 2
      },
      "http.response_time.2xx": {
        "min": 0,
        "max": 33,
        "count": 9000,
        "mean": 0.3,
        "p50": 0,
        "median": 0,
        "p75": 1,
        "p90": 1,
        "p95": 1,
        "p99": 1,
        "p999": 2
      },
      "plugins.metrics-by-endpoint.response_time./posts": {
        "min": 0,
        "max": 33,
        "count": 3000,
        "mean": 0.4,
        "p50": 0,
        "median": 0,
        "p75": 1,
        "p90": 1,
        "p95": 1,
        "p99": 1,
        "p999": 22.9
      },
      "plugins.metrics-by-endpoint.response_time./users": {
        "min": 0,
        "max": 3,
        "count": 3000,
        "mean": 0.3,
        "p50": 0,
        "median": 0,
        "p75": 1,
        "p90": 1,
        "p95": 1,
        "p99": 1,
        "p999": 1
      },
      "plugins.metrics-by-endpoint.response_time./comments": {
        "min": 0,
        "max": 2,
        "count": 3000,
        "mean": 0.3,
        "p50": 0,
        "median": 0,
        "p75": 1,
        "p90": 1,
        "p95": 1,
        "p99": 1,
        "p999": 2
      },
      "vusers.session_length": {
        "min": 2,
        "max": 51,
        "count": 3000,
        "mean": 3.2,
        "p50": 2.9,
        "median": 2.9,
        "p75": 3.2,
        "p90": 3.7,
        "p95": 4.4,
        "p99": 15.6,
        "p999": 31.5
      }
    },
    "histograms": {
      "http.response_time": {
        "min": 0,
        "max": 33,
        "count": 9000,
        "mean": 0.3,
        "p50": 0,
        "median": 0,
        "p75": 1,
        "p90": 1,
        "p95": 1,
        "p99": 1,
        "p999": 2
      },
      "http.response_time.2xx": {
        "min": 0,
        "max": 33,
        "count": 9000,
        "mean": 0.3,
        "p50": 0,
        "median": 0,
        "p75": 1,
        "p90": 1,
        "p95": 1,
        "p99": 1,
        "p999": 2
      },
      "plugins.metrics-by-endpoint.response_time./posts": {
        "min": 0,
        "max": 33,
        "count": 3000,
        "mean": 0.4,
        "p50": 0,
        "median": 0,
        "p75": 1,
        "p90": 1,
        "p95": 1,
        "p99": 1,
        "p999": 22.9
      },
      "plugins.metrics-by-endpoint.response_time./users": {
        "min": 0,
        "max": 3,
        "count": 3000,
        "mean": 0.3,
        "p50": 0,
        "median": 0,
        "p75": 1,
        "p90": 1,
        "p95": 1,
        "p99": 1,
        "p999": 1
      },
      "plugins.metrics-by-endpoint.response_time./comments": {
        "min": 0,
        "max": 2,
        "count": 3000,
        "mean": 0.3,
        "p50": 0,
        "median": 0,
        "p75": 1,
        "p90": 1,
        "p95": 1,
        "p99": 1,
        "p999": 2
      },
      "vusers.session_length": {
        "min": 2,
        "max": 51,
        "count": 3000,
        "mean": 3.2,
        "p50": 2.9,
        "median": 2.9,
        "p75": 3.2,
        "p90": 3.7,
        "p95": 4.4,
        "p99": 15.6,
        "p999": 31.5
      }
    }
  },
  "intermediate": [
    {
      "counters": {
        "vusers.created_by_name.Cenário 100 usuários": 367,
        "vusers.created": 367,
        "http.requests": 1099,
        "http.codes.200": 1098,
        "http.responses": 1098,
        "http.downloaded_bytes": 73566,
        "plugins.metrics-by-endpoint./posts.codes.200": 366,
        "plugins.metrics-by-endpoint./users.codes.200": 366,
        "plugins.metrics-by-endpoint./comments.codes.200": 366,
        "vusers.failed": 0,
        "vusers.completed": 366
      },
      "rates": {
        "http.request_rate": 330
      },
      "http.request_rate": null,
      "firstCounterAt": 1763429065721,
      "firstHistogramAt": 1763429065734,
      "lastCounterAt": 1763429069999,
      "lastHistogramAt": 1763429069988,
      "firstMetricAt": 1763429065721,
      "lastMetricAt": 1763429069999,
      "period": "1763429060000",
      "summaries": {
        "http.response_time": {
          "min": 0,
          "max": 33,
          "count": 1098,
          "mean": 0.5,
          "p50": 0,
          "median": 0,
          "p75": 1,
          "p90": 1,
          "p95": 1,
          "p99": 1,
          "p999": 27.9
        },
        "http.response_time.2xx": {
          "min": 0,
          "max": 33,
          "count": 1098,
          "mean": 0.5,
          "p50": 0,
          "median": 0,
          "p75": 1,
          "p90": 1,
          "p95": 1,
          "p99": 1,
          "p999": 27.9
        },
        "plugins.metrics-by-endpoint.response_time./posts": {
          "min": 0,
          "max": 33,
          "count": 366,
          "mean": 0.9,
          "p50": 0,
          "median": 0,
          "p75": 1,
          "p90": 1,
          "p95": 1,
          "p99": 19.1,
          "p999": 30.9
        },
        "plugins.metrics-by-endpoint.response_time./users": {
          "min": 0,
          "max": 1,
          "count": 366,
          "mean": 0.4,
          "p50": 0,
          "median": 0,
          "p75": 1,
          "p90": 1,
          "p95": 1,
          "p99": 1,
          "p999": 1
        },
        "plugins.metrics-by-endpoint.response_time./comments": {
          "min": 0,
          "max": 1,
          "count": 366,
          "mean": 0.3,
          "p50": 0,
          "median": 0,
          "p75": 1,
          "p90": 1,
          "p95": 1,
          "p99": 1,
          "p999": 1
        },
        "vusers.session_length": {
          "min": 2.5,
          "max": 51,
          "count": 366,
          "mean": 5.6,
          "p50": 3.5,
          "median": 3.5,
          "p75": 5,
          "p90": 15,
          "p95": 17.3,
          "p99": 26.8,
          "p999": 37.7
        }
      },
      "histograms": {
        "http.response_time": {
          "min": 0,
          "max": 33,
          "count": 1098,
          "mean": 0.5,
          "p50": 0,
          "median": 0,
          "p75": 1,
          "p90": 1,
          "p95": 1,
          "p99": 1,
          "p999": 27.9
        },
        "http.response_time.2xx": {
          "min": 0,
          "max": 33,
          "count": 1098,
          "mean": 0.5,
          "p50": 0,
          "median": 0,
          "p75": 1,
          "p90": 1,
          "p95": 1,
          "p99": 1,
          "p999": 27.9
        },
        "plugins.metrics-by-endpoint.response_time./posts": {
          "min": 0,
          "max": 33,
          "count": 366,
          "mean": 0.9,
          "p50": 0,
          "median": 0,
          "p75": 1,
          "p90": 1,
          "p95": 1,
          "p99": 19.1,
          "p999": 30.9
        },
        "plugins.metrics-by-endpoint.response_time./users": {
          "min": 0,
          "max": 1,
          "count": 366,
          "mean": 0.4,
          "p50": 0,
          "median": 0,
          "p75": 1,
          "p90": 1,
          "p95": 1,
          "p99": 1,
          "p999": 1
        },
        "plugins.metrics-by-endpoint.response_time./comments": {
          "min": 0,
          "max": 1,
          "count": 366,
          "mean": 0.3,
          "p50": 0,
          "median": 0,
          "p75": 1,
          "p90": 1,
          "p95": 1,
          "p99": 1,
          "p999": 1
        },
        "vusers.session_length": {
          "min": 2.5,
          "max": 51,
          "count": 366,
          "mean": 5.6,
          "p50": 3.5,
          "median": 3.5,
          "p75": 5,
          "p90": 15,
          "p95": 17.3,
          "p99": 26.8,
          "p999": 37.7
        }
      }
    },
    {
      "counters": {
        "vusers.created_by_name.Cenário 100 usuários": 1000,
        "vusers.created": 1000,
        "http.requests": 3001,
        "http.codes.200": 3001,
        "http.responses": 3001,
        "http.downloaded_bytes": 201086,
        "plugins.metrics-by-endpoint./posts.codes.200": 1001,
        "plugins.metrics-by-endpoint./users.codes.200": 1000,
        "plugins.metrics-by-endpoint./comments.codes.200": 1000,
        "vusers.failed": 0,
        "vusers.completed": 1000
      },
      "rates": {
        "http.request_rate": 300
      },
      "http.request_rate": null,
      "firstCounterAt": 1763429070000,
      "firstHistogramAt": 1763429070000,
      "lastCounterAt": 1763429079999,
      "lastHistogramAt": 1763429079999,
      "firstMetricAt": 1763429070000,
      "lastMetricAt": 1763429079999,
      "period": "1763429070000",
      "summaries": {
        "http.response_time": {
          "min": 0,
          "max": 3,
          "count": 3001,
          "mean": 0.3,
          "p50": 0,
          "median": 0,
          "p75": 1,
          "p90": 1,
          "p95": 1,
          "p99": 1,
          "p999": 2
        },
        "http.response_time.2xx": {
          "min": 0,
          "max": 3,
          "count": 3001,
          "mean": 0.3,
          "p50": 0,
          "median": 0,
          "p75": 1,
          "p90": 1,
          "p95": 1,
          "p99": 1,
          "p999": 2
        },
        "plugins.metrics-by-endpoint.response_time./posts": {
          "min": 0,
          "max": 2,
          "count": 1001,
          "mean": 0.4,
          "p50": 0,
          "median": 0,
          "p75": 1,
          "p90": 1,
          "p95": 1,
          "p99": 1,
          "p999": 2
        },
        "plugins.metrics-by-endpoint.response_time./users": {
          "min": 0,
          "max": 3,
          "count": 1000,
          "mean": 0.3,
          "p50": 0,
          "median": 0,
          "p75": 1,
          "p90": 1,
          "p95": 1,
          "p99": 1,
          "p999": 1
        },
        "plugins.metrics-by-endpoint.response_time./comments": {
          "min": 0,
          "max": 2,
          "count": 1000,
          "mean": 0.3,
          "p50": 0,
          "median": 0,
          "p75": 1,
          "p90": 1,
          "p95": 1,
          "p99": 1,
          "p999": 2
        },
        "vusers.session_length": {
          "min": 2,
          "max": 5.8,
          "count": 1000,
          "mean": 3,
          "p50": 2.9,
          "median": 2.9,
          "p75": 3.2,
          "p90": 3.5,
          "p95": 3.8,
          "p99": 4.6,
          "p999": 5.6
        }
      },
      "histograms": {
        "http.response_time": {
          "min": 0,
          "max": 3,
          "count": 3001,
          "mean": 0.3,
          "p50": 0,
          "median": 0,
          "p75": 1,
          "p90": 1,
          "p95": 1,
          "p99": 1,
          "p999": 2
        },
        "http.response_time.2xx": {
          "min": 0,
          "max": 3,
          "count": 3001,
          "mean": 0.3,
          "p50": 0,
          "median": 0,
          "p75": 1,
          "p90": 1,
          "p95": 1,
          "p99": 1,
          "p999": 2
        },
        "plugins.metrics-by-endpoint.response_time./posts": {
          "min": 0,
          "max": 2,
          "count": 1001,
          "mean": 0.4,
          "p50": 0,
          "median": 0,
          "p75": 1,
          "p90": 1,
          "p95": 1,
          "p99": 1,
          "p999": 2
        },
        "plugins.metrics-by-endpoint.response_time./users": {
          "min": 0,
          "max": 3,
          "count": 1000,
          "mean": 0.3,
          "p50": 0,
          "median": 0,
          "p75": 1,
          "p90": 1,
          "p95": 1,
          "p99": 1,
          "p999": 1
        },
        "plugins.metrics-by-endpoint.response_time./comments": {
          "min": 0,
          "max": 2,
          "count": 1000,
          "mean": 0.3,
          "p50": 0,
          "median": 0,
          "p75": 1,
          "p90": 1,
          "p95": 1,
          "p99": 1,
          "p999": 2
        },
        "vusers.session_length": {
          "min": 2,
          "max": 5.8,
          "count": 1000,
          "mean": 3,
          "p50": 2.9,
          "median": 2.9,
          "p75": 3.2,
          "p90": 3.5,
          "p95": 3.8,
          "p99": 4.6,
          "p999": 5.6
        }
      }
    },
    {
      "counters": {
        "vusers.created_by_name.Cenário 100 usuários": 1000,
        "vusers.created": 1000,
        "http.requests": 2999,
        "http.codes.200": 3000,
        "http.responses": 3000,
        "http.downloaded_bytes": 201000,
        "plugins.metrics-by-endpoint./posts.codes.200": 1000,
        "plugins.metrics-by-endpoint./users.codes.200": 1000,
        "plugins.metrics-by-endpoint./comments.codes.200": 1000,
        "vusers.failed": 0,
        "vusers.completed": 1000
      },
      "rates": {
        "http.request_rate": 300
      },
      "http.request_rate": null,
      "firstCounterAt": 1763429080000,
      "firstHistogramAt": 1763429080000,
      "lastCounterAt": 1763429089999,
      "lastHistogramAt": 1763429089999,
      "firstMetricAt": 1763429080000,
      "lastMetricAt": 1763429089999,
      "period": "1763429080000",
      "summaries": {
        "http.response_time": {
          "min": 0,
          "max": 2,
          "count": 3000,
          "mean": 0.3,
          "p50": 0,
          "median": 0,
          "p75": 1,
          "p90": 1,
          "p95": 1,
          "p99": 1,
          "p999": 1
        },
        "http.response_time.2xx": {
          "min": 0,
          "max": 2,
          "count": 3000,
          "mean": 0.3,
          "p50": 0,
          "median": 0,
          "p75": 1,
          "p90": 1,
          "p95": 1,
          "p99": 1,
          "p999": 1
        },
        "plugins.metrics-by-endpoint.response_time./posts": {
          "min": 0,
          "max": 1,
          "count": 1000,
          "mean": 0.4,
          "p50": 0,
          "median": 0,
          "p75": 1,
          "p90": 1,
          "p95": 1,
          "p99": 1,
          "p999": 1
        },
        "plugins.metrics-by-endpoint.response_time./users": {
          "min": 0,
          "max": 2,
          "count": 1000,
          "mean": 0.3,
          "p50": 0,
          "median": 0,
          "p75": 1,
          "p90": 1,
          "p95": 1,
          "p99": 1,
          "p999": 1
        },
        "plugins.metrics-by-endpoint.response_time./comments": {
          "min": 0,
          "max": 2,
          "count": 1000,
          "mean": 0.3,
          "p50": 0,
          "median": 0,
          "p75": 1,
          "p90": 1,
          "p95": 1,
          "p99": 1,
          "p999": 1
        },
        "vusers.session_length": {
          "min": 2,
          "max": 7.3,
          "count": 1000,
          "mean": 2.8,
          "p50": 2.7,
          "median": 2.7,
          "p75": 3,
          "p90": 3.4,
          "p95": 3.7,
          "p99": 4.5,
          "p999": 5.8
        }
      },
      "histograms": {
        "http.response_time": {
          "min": 0,
          "max": 2,
          "count": 3000,
          "mean": 0.3,
          "p50": 0,
          "median": 0,
          "p75": 1,
          "p90": 1,
          "p95": 1,
          "p99": 1,
          "p999": 1
        },
        "http.response_time.2xx": {
          "min": 0,
          "max": 2,
          "count": 3000,
          "mean": 0.3,
          "p50": 0,
          "median": 0,
          "p75": 1,
          "p90": 1,
          "p95": 1,
          "p99": 1,
          "p999": 1
        },
        "plugins.metrics-by-endpoint.response_time./posts": {
          "min": 0,
          "max": 1,
          "count": 1000,
          "mean": 0.4,
          "p50": 0,
          "median": 0,
          "p75": 1,
          "p90": 1,
          "p95": 1,
          "p99": 1,
          "p999": 1
        },
        "plugins.metrics-by-endpoint.response_time./users": {
          "min": 0,
          "max": 2,
          "count": 1000,
          "mean": 0.3,
          "p50": 0,
          "median": 0,
          "p75": 1,
          "p90": 1,
          "p95": 1,
          "p99": 1,
          "p999": 1
        },
        "plugins.metrics-by-endpoint.response_time./comments": {
          "min": 0,
          "max": 2,
          "count": 1000,
          "mean": 0.3,
          "p50": 0,
          "median": 0,
          "p75": 1,
          "p90": 1,
          "p95": 1,
          "p99": 1,
          "p999": 1
        },
        "vusers.session_length": {
          "min": 2,
          "max": 7.3,
          "count": 1000,
          "mean": 2.8,
          "p50": 2.7,
          "median": 2.7,
          "p75": 3,
          "p90": 3.4,
          "p95": 3.7,
          "p99": 4.5,
          "p999": 5.8
        }
      }
    },
    {
      "counters": {
        "vusers.created_by_name.Cenário 100 usuários": 633,
        "vusers.created": 633,
        "http.requests": 1901,
        "http.codes.200": 1901,
        "http.responses": 1901,
        "http.downloaded_bytes": 127348,
        "plugins.metrics-by-endpoint./posts.codes.200": 633,
        "plugins.metrics-by-endpoint./users.codes.200": 634,
        "plugins.metrics-by-endpoint./comments.codes.200": 634,
        "vusers.failed": 0,
        "vusers.completed": 634
      },
      "rates": {
        "http.request_rate": 311
      },
      "http.request_rate": null,
      "firstCounterAt": 1763429090000,
      "firstHistogramAt": 1763429090000,
      "lastCounterAt": 1763429096987,
      "lastHistogramAt": 1763429096987,
      "firstMetricAt": 1763429090000,
      "lastMetricAt": 1763429096987,
      "period": "1763429090000",
      "summaries": {
        "http.response_time": {
          "min": 0,
          "max": 2,
          "count": 1901,
          "mean": 0.3,
          "p50": 0,
          "median": 0,
          "p75": 1,
          "p90": 1,
          "p95": 1,
          "p99": 1,
          "p999": 2
        },
        "http.response_time.2xx": {
          "min": 0,
          "max": 2,
          "count": 1901,
          "mean": 0.3,
          "p50": 0,
          "median": 0,
          "p75": 1,
          "p90": 1,
          "p95": 1,
          "p99": 1,
          "p999": 2
        },
        "plugins.metrics-by-endpoint.response_time./posts": {
          "min": 0,
          "max": 2,
          "count": 633,
          "mean": 0.4,
          "p50": 0,
          "median": 0,
          "p75": 1,
          "p90": 1,
          "p95": 1,
          "p99": 1,
          "p999": 2
        },
        "plugins.metrics-by-endpoint.response_time./users": {
          "min": 0,
          "max": 1,
          "count": 634,
          "mean": 0.3,
          "p50": 0,
          "median": 0,
          "p75": 1,
          "p90": 1,
          "p95": 1,
          "p99": 1,
          "p999": 1
        },
        "plugins.metrics-by-endpoint.response_time./comments": {
          "min": 0,
          "max": 2,
          "count": 634,
          "mean": 0.3,
          "p50": 0,
          "median": 0,
          "p75": 1,
          "p90": 1,
          "p95": 1,
          "p99": 1,
          "p999": 2
        },
        "vusers.session_length": {
          "min": 2,
          "max": 7.8,
          "count": 634,
          "mean": 2.8,
          "p50": 2.7,
          "median": 2.7,
          "p75": 3,
          "p90": 3.4,
          "p95": 3.6,
          "p99": 4.4,
          "p999": 5
        }
      },
      "histograms": {
        "http.response_time": {
          "min": 0,
          "max": 2,
          "count": 1901,
          "mean": 0.3,
          "p50": 0,
          "median": 0,
          "p75": 1,
          "p90": 1,
          "p95": 1,
          "p99": 1,
          "p999": 2
        },
        "http.response_time.2xx": {
          "min": 0,
          "max": 2,
          "count": 1901,
          "mean": 0.3,
          "p50": 0,
          "median": 0,
          "p75": 1,
          "p90": 1,
          "p95": 1,
          "p99": 1,
          "p999": 2
        },
        "plugins.metrics-by-endpoint.response_time./posts": {
          "min": 0,
          "max": 2,
          "count": 633,
          "mean": 0.4,
          "p50": 0,
          "median": 0,
          "p75": 1,
          "p90": 1,
          "p95": 1,
          "p99": 1,
          "p999": 2
        },
        "plugins.metrics-by-endpoint.response_time./users": {
          "min": 0,
          "max": 1,
          "count": 634,
          "mean": 0.3,
          "p50": 0,
          "median": 0,
          "p75": 1,
          "p90": 1,
          "p95": 1,
          "p99": 1,
          "p999": 1
        },
        "plugins.metrics-by-endpoint.response_time./comments": {
          "min": 0,
          "max": 2,
          "count": 634,
          "mean": 0.3,
          "p50": 0,
          "median": 0,
          "p75": 1,
          "p90": 1,
          "p95": 1,
          "p99": 1,
          "p999": 2
        },
        "vusers.session_length": {
          "min": 2,
          "max": 7.8,
          "count": 634,
          "mean": 2.8,
          "p50": 2.7,
          "median": 2.7,
          "p75": 3,
          "p90": 3.4,
          "p95": 3.6,
          "p99": 4.4,
          "p999": 5
        }
      }
    }
  ]
}